{
    "name": "Export DTM to RGB TIFF",
    "function": "pyat.dtm.export.dtm_to_tiff_rgba.Dtm2TiffRgba",
    "help": "https://fleet.gitlab-pages.ifremer.fr/data-processing/globe/globe-documentation/pyat/dtm/export/dtm_to_tiff_rgba.html",
    "parameters": [
        {
            "name": "i_paths",
            "key": "-i",
            "long_key": "--i_paths",
            "help": "Input file list (*.dtm.nc)",
            "nargs": "+",
            "type": "infile(content_type=DTM_NETCDF_4)"
        },
        {
            "name": "o_paths",
            "key": "-o",
            "long_key": "--o_paths",
            "help": "Output file list (.tif)",
            "nargs": "+",
            "type": "outfile(extension=tif)"
        },
        {
            "name": "overwrite",
            "key": "-ow",
            "long_key": "--overwrite",
            "help": "Allow to overwrite file if already exists.",
            "type": "outfile#overwrite"
        }
    ]
}
